mcp_server_shiran/__init__.py
mcp_server_shiran/__main__.py
mcp_server_shiran/server.py
mcp_server_shiran-0.1.1.dist-info/METADATA
mcp_server_shiran-0.1.1.dist-info/WHEEL
mcp_server_shiran-0.1.1.dist-info/entry_points.txt
mcp_server_shiran-0.1.1.dist-info/top_level.txt
mcp_server_shiran-0.1.1.dist-info/RECORD
