Metadata-Version: 2.4
Name: mcp-server-shiran
Version: 0.1.1
Summary: 实现天气weather功能的MCP工具
Requires-Python: >=3.12
Requires-Dist: dotenv>=0.9.9
Requires-Dist: mcp>=1.16.0
Requires-Dist: openai>=2.2.0
